web_search/__init__.py
web_search/blocks.py
web_search/config.py
web_search/web_searcher.py
web_search/example/roleplayWithWebSearch.yaml
chatgpt_mirai_qq_bot_web_search-0.3.2.dist-info/LICENSE
chatgpt_mirai_qq_bot_web_search-0.3.2.dist-info/METADATA
chatgpt_mirai_qq_bot_web_search-0.3.2.dist-info/WHEEL
chatgpt_mirai_qq_bot_web_search-0.3.2.dist-info/entry_points.txt
chatgpt_mirai_qq_bot_web_search-0.3.2.dist-info/top_level.txt
chatgpt_mirai_qq_bot_web_search-0.3.2.dist-info/RECORD
