Metadata-Version: 2.1
Name: chatgpt-mirai-qq-bot-web-search
Version: 0.3.2
Summary: WebSearch adapter for lss233/chatgpt-mirai-qq-bot
Home-page: https://github.com/chuanSir123/web_search
Author: chuanSir
Author-email: 416448943@qq.com
Project-URL: Bug Tracker, https://github.com/chuanSir123/web_search/issues
Project-URL: Documentation, https://github.com/chuanSir123/web_search/wiki
Project-URL: Source Code, https://github.com/chuanSir123/web_search
Classifier: Programming Language :: Python :: 3
Classifier: License :: OSI Approved :: GNU Affero General Public License v3
Classifier: Operating System :: OS Independent
Requires-Python: >=3.8
License-File: LICENSE
Requires-Dist: playwright
Requires-Dist: trafilatura
Requires-Dist: lxml-html-clean
Requires-Dist: kirara-ai>=3.2.0
